digaws/__init__.py
digaws/digaws.py
digaws-1.0.8.dist-info/METADATA
digaws-1.0.8.dist-info/WHEEL
digaws-1.0.8.dist-info/entry_points.txt
digaws-1.0.8.dist-info/licenses/LICENSE
digaws-1.0.8.dist-info/RECORD
