Metadata-Version: 2.4
Name: digaws
Version: 1.0.8
Summary: Look up canonical information for AWS IP addresses and networks
Project-URL: Homepage, http://github.com/dcarrillo/digaws
Project-URL: Repository, http://github.com/dcarrillo/digaws
Author-email: Daniel Carrillo <daniel.carrillo@gmail.com>
License: Apache Software License
License-File: LICENSE
Keywords: aws,dns,ip,lookup,network
Classifier: License :: OSI Approved :: Apache Software License
Classifier: Operating System :: OS Independent
Classifier: Programming Language :: Python :: 3
Requires-Python: >=3.10
Requires-Dist: python-dateutil~=2.9
Requires-Dist: requests~=2.25
